anssdk/__init__.py
anssdk/address.py
anssdk/ans.py
anssdk/constants.py
anssdk/dot_algo_name_record.py
anssdk/name.py
anssdk/resolver.py
anssdk/transactions.py
anssdk/helper/__init__.py
anssdk/helper/validation.py
anssdk/tests/__init__.py
anssdk/tests/ans_helper.py
anssdk/tests/test.py
anssdk-0.2.0.dist-info/LICENSE
anssdk-0.2.0.dist-info/METADATA
anssdk-0.2.0.dist-info/WHEEL
anssdk-0.2.0.dist-info/top_level.txt
anssdk-0.2.0.dist-info/RECORD
