Metadata-Version: 2.1
Name: anssdk
Version: 0.2.0
Summary: Python SDK to resolve ANS .algo names
Home-page: UNKNOWN
Author: Algorand Name Service
Author-email: contact@algonameservice.com
License: UNKNOWN
Keywords: python,algorand,algorand name service,py-sdk,name service,.algo
Platform: UNKNOWN
